roltrilinos
