Metadata-Version: 1.0
Name: roltrilinos
Version: 0.0.4
Summary: A C++ package for large scale optimization.
Home-page: UNKNOWN
Author: Drew Kouri, Denis Ridzal, Greg von Winckel
Author-email: rol-developers@software.sandia.gov
License: UNKNOWN
Platform: UNKNOWN
